ector/__init__.py
ector/core.py
ector/dictionary.py
ector/triggers_fillers.py
ector-0.1.2.dist-info/METADATA
ector-0.1.2.dist-info/WHEEL
ector-0.1.2.dist-info/RECORD
