Metadata-Version: 2.3
Name: ector
Version: 0.1.2
Summary: Extract from a given long text input, eCommerce products and price budget.
Author: sanix-darker
Author-email: s4nixd@gmail.com
Requires-Python: >=3.10,<3.13
Classifier: Programming Language :: Python :: 3
Classifier: Programming Language :: Python :: 3.10
Classifier: Programming Language :: Python :: 3.11
Classifier: Programming Language :: Python :: 3.12
Requires-Dist: spacy (>=3.8.4,<4.0.0)
